libqcanvas/__init__.py
libqcanvas/alembic/README
libqcanvas/alembic/env.py
libqcanvas/alembic/script.py.mako
libqcanvas/alembic/versions/3c4e800178ab_initial_revision.py
libqcanvas/alembic.ini
libqcanvas/database/__init__.py
libqcanvas/database/data_monolith.py
libqcanvas/database/qcanvas_database.py
libqcanvas/database/resource_links/__init__.py
libqcanvas/database/resource_links/decorators.py
libqcanvas/database/resource_links/ornamental_mixins.py
libqcanvas/database/resource_links/ornamental_mixins.pyi
libqcanvas/database/resource_links/resource_link_manipulators.py
libqcanvas/database/tables/__init__.py
libqcanvas/database/tables/_tz_datetime.py
libqcanvas/database/tables/base.py
libqcanvas/database/tables/canvas_database_types.py
libqcanvas/database/tables/content_group.py
libqcanvas/database/tables/course_content_item.py
libqcanvas/database/tables/creation_date.py
libqcanvas/database/tables/id.py
libqcanvas/database/tables/modification_date.py
libqcanvas/database/tables/module_page_type.py
libqcanvas/database/tables/resource.py
libqcanvas/database/tables/resource_download_state.py
libqcanvas/database/tables/resource_link_state.py
libqcanvas/gql_queries/__init__.py
libqcanvas/gql_queries/assignment_group_index.graphql
libqcanvas/gql_queries/assignment_group_index.py
libqcanvas/gql_queries/assignment_index.graphql
libqcanvas/gql_queries/assignment_index.py
libqcanvas/gql_queries/attachment.graphql
libqcanvas/gql_queries/attachment.py
libqcanvas/gql_queries/canvas_introspection.json
libqcanvas/gql_queries/course_index.graphql
libqcanvas/gql_queries/course_index.py
libqcanvas/gql_queries/course_mail.gql
libqcanvas/gql_queries/course_mail.py
libqcanvas/gql_queries/graphql.config.yml
libqcanvas/gql_queries/module_index.graphql
libqcanvas/gql_queries/module_index.py
libqcanvas/gql_queries/schema.graphql
libqcanvas/net/__init__.py
libqcanvas/net/canvas/__init__.py
libqcanvas/net/canvas/canvas_data_aggregator.py
libqcanvas/net/canvas/canvas_page_loader.py
libqcanvas-2026.1.20.dist-info/METADATA
libqcanvas-2026.1.20.dist-info/WHEEL
libqcanvas-2026.1.20.dist-info/RECORD
