Metadata-Version: 2.1
Name: libqcanvas
Version: 2026.1.20
Summary: Does most of the heavy lifting for qcanvas
Author: QCanvas
Author-email: QCanvas@noreply.codeberg.org
Requires-Python: >=3.12,<4.0
Classifier: Programming Language :: Python :: 3
Classifier: Programming Language :: Python :: 3.12
Classifier: Programming Language :: Python :: 3.13
Requires-Dist: SQLAlchemy (>=2.0.29,<3.0.0)
Requires-Dist: aiofile (>=3.9.0,<4.0.0)
Requires-Dist: alembic (>=1.13.3,<2.0.0)
Requires-Dist: asynchronize (>=0.0.1,<0.0.2)
Requires-Dist: asynctaskpool (>=0.2.0,<0.3.0)
Requires-Dist: beautifulsoup4 (>=4.12.3,<5.0.0)
Requires-Dist: gql (>=3.5.1,<4.0.0)
Requires-Dist: httpx[http2] (>=0.28.1,<0.29.0)
Requires-Dist: libqcanvas-clients (>2026.0.0)
Requires-Dist: pydantic (>=2.7.0,<3.0.0)
Requires-Dist: yt-dlp (>=2024.4.9)
